bmi160.py
circuitpython_bmi160-0.2.9.dist-info/LICENSE
circuitpython_bmi160-0.2.9.dist-info/METADATA
circuitpython_bmi160-0.2.9.dist-info/WHEEL
circuitpython_bmi160-0.2.9.dist-info/top_level.txt
circuitpython_bmi160-0.2.9.dist-info/RECORD
