Metadata-Version: 2.1
Name: circuitpython-bmi160
Version: 0.2.9
Summary: Driver for the BMI160 sensor
Author-email: "Jose D. Montoya" <bmi160@mailmeto.mozmail.com>
License: MIT
Project-URL: Homepage, https://github.com/jposada202020/CircuitPython_BMI160
Keywords: circuitpython,bmi160,acceleration,gyro,magnetic,BMI160,python,step,sensor
Classifier: Intended Audience :: Developers
Classifier: Topic :: Software Development :: Libraries
Classifier: Topic :: Software Development :: Embedded Systems
Classifier: Topic :: System :: Hardware
Classifier: License :: OSI Approved :: MIT License
Classifier: Programming Language :: Python :: 3
License-File: LICENSE
Requires-Dist: Adafruit-Blinka
Requires-Dist: adafruit-circuitpython-busdevice
Requires-Dist: adafruit-circuitpython-register
Provides-Extra: optional
